{
    "appearance": {
        "skin_tone": {
            "enabled": true,
            "base": "Deep",
            "undertone": "Neutral",
            "depth_level": "Deep",
            "tanning": "None",
            "freckles": {
                "enabled": false
            },
            "complexion_finish": "Natural",
            "blemish_policy": "Realistic",
            "consistency_guards": {
                "lock_skin_tone": true,
                "avoid_color_shift_from_lighting": true
            },
            "constraints": []
        }
    }
}